{
	"name": "Sales_demo",
	"properties": {
		"linkedServiceName": {
			"referenceName": "AzureDataLakeStore1",
			"type": "LinkedServiceReference"
		},
		"annotations": [],
		"type": "Json",
		"typeProperties": {
			"location": {
				"type": "AzureDataLakeStoreLocation",
				"fileName": "Sales_demo.json",
				"folderPath": "Configuration"
			}
		},
		"schema": {
			"type": "object",
			"properties": {
				"Case": {
					"type": "array",
					"items": {
						"type": "object",
						"properties": {
							"folder_path": {
								"type": "string"
							},
							"source_file_name": {
								"type": "string"
							}
						}
					}
				}
			}
		}
	},
	"type": "Microsoft.DataFactory/factories/datasets"
}